game_of_life_cli/__init__.py
game_of_life_cli/__main__.py
game_of_life_cli-0.1.1.dist-info/METADATA
game_of_life_cli-0.1.1.dist-info/WHEEL
game_of_life_cli-0.1.1.dist-info/RECORD
