Metadata-Version: 2.1
Name: game-of-life-cli
Version: 0.1.1
Summary: An implementation of Conway's Game of Life in Python
License: Apache-2.0
Author: Bruno Conde Kind
Author-email: condekind@users.noreply.github.com
Requires-Python: >=3.12,<4.0
Classifier: License :: OSI Approved :: Apache Software License
Classifier: Programming Language :: Python :: 3
Classifier: Programming Language :: Python :: 3.12
